dndbuddy_basic/__init__.py
dndbuddy_basic/alignments.py
dndbuddy_basic/armor.py
dndbuddy_basic/combat.py
dndbuddy_basic/createcharacter.py
dndbuddy_basic/hitdice.py
dndbuddy_basic/magic.py
dndbuddy_basic/rolldice.py
dndbuddy_basic/weapons.py
dndbuddy_basic-0.0.1.dist-info/METADATA
dndbuddy_basic-0.0.1.dist-info/WHEEL
dndbuddy_basic-0.0.1.dist-info/top_level.txt
dndbuddy_basic-0.0.1.dist-info/RECORD
